MANIFEST.in
README.markdown
setup.py
test/test_foo.py
webdriverwrapper/__init__.py
webdriverwrapper/decorators.py
webdriverwrapper/download.py
webdriverwrapper/errors.py
webdriverwrapper/exceptions.py
webdriverwrapper/forms.py
webdriverwrapper/info.py
webdriverwrapper/wrapper.py
webdriverwrapper.egg-info/PKG-INFO
webdriverwrapper.egg-info/SOURCES.txt
webdriverwrapper.egg-info/dependency_links.txt
webdriverwrapper.egg-info/requires.txt
webdriverwrapper.egg-info/top_level.txt
webdriverwrapper/pytest/__init__.py
webdriverwrapper/pytest/conftest.py
webdriverwrapper/unittest/__init__.py
webdriverwrapper/unittest/testcase.py