Metadata-Version: 2.1
Name: webdriverwrapper
Version: 2.8.0
Summary: Better interface for WebDriver (Selenium 2).
Home-page: https://github.com/horejsek/python-webdriverwrapper
Author: Michal Horejsek
Author-email: horejsekmichal@gmail.com
License: PSF
Platform: UNKNOWN
Classifier: Programming Language :: Python :: 3
Classifier: License :: OSI Approved :: MIT License
Classifier: Operating System :: OS Independent
Classifier: Development Status :: 5 - Production/Stable
Classifier: Intended Audience :: Developers
Classifier: Topic :: Software Development :: Libraries :: Python Modules
Classifier: Topic :: Software Development :: Testing
Provides-Extra: devel
Provides-Extra: suggestion
